{
  "breadcrumb": {
    "right": "تکنسین‌ها / علی رهبر عبدالرزاق قرنی",
    "left": "گزارش مشخصات کالا یا موارد قانونی"
  },
  "technician": {
    "nameFa": "علی رهبر عبدالرزاق قرنی",
    "nameEn": "Ali Rahbar Abdorazagh ghormi",
    "verifiedText": "تکنسین تایید شده توسط والدنت",
    "avatarUrl": "assets/images/technician.png"
  },
  "stats": {
    "questions": 3,
    "reviews": 2,
    "projects": 3,
    "rating": 5,
    "votes": 2
  },
  "primarySpecialty": {
    "title": "تخصص اصلی",
    "name": "متخصص تعمیر هندپیس",
    "desc": "مهارت بالا در تعمیر و نگهداری هندپیس‌های سرعت بالا/پایین و سیستم‌های میکروموتور."
  },
  "otherSpecialtiesTitle": "سایر تخصص‌ها",
  "otherSpecialties": [
    "تکنسین نگهداری و تعمیرات تجهیزات دندانپزشکی",
    "تکنسین یونیت و صندلی دندانپزشکی",
    "متخصص استریلیزاسیون و اوتوکلاوها",
    "تکنسین تجهیزات تصویربرداری و رادیولوژی دندانپزشکی"
  ],
  "serviceLocationsTitle": "ارائه خدمات برای استان‌های",
  "serviceLocations": [
    { "province": "قزوین", "city": "قزوین، تاکستان، آبیک، قزوین" },
    { "province": "البرز", "city": "کرج، فردیس، گوهردشت" },
    { "province": "تهران", "city": "تهران، کرج، شهریار، دماوند" }
  ],
  "brandsTitle": "برندهای تخصصی",
  "brands": [
    { "name": "KaVo", "logoUrl": "assets/images/KaVo.png" },
    { "name": "KaVo", "logoUrl": "assets/images/KaVo.png" },
    { "name": "Dentsply Sirona", "logoUrl": "assets/images/Dentsply.png" },
    { "name": "Vatech", "logoUrl": "assets/images/Vatech.png" }
  ],
  "reportTitle": "گزارش مشخصات کالا یا موارد قانونی",
  "profileTitle": "مشخصات متخصص",
  "profileSpecs": [
    { "label": "نام و نام خانوادگی", "value": "علی رهبر عبدالرزاق قرنی" },
    { "label": "سن", "value": "۳۸ سال" },
    { "label": "مدرک تحصیلی", "value": "متخصص مهندسی پزشکی" },
    { "label": "شماره‌های تماس", "value": "۰۲۱ ۸۸۴۰ ۳۲۴۴  -  ۰۹۱۲ ۴۴۴ ۳۰۱۷" },
    { "label": "ایمیل", "value": "contact@alirahbar.ir", "isLink": true, "linkPrefix": "mailto:" },
    { "label": "وبسایت", "value": "alirahbar.ir", "isLink": true, "linkPrefix": "https://" },
    { "label": "آدرس", "value": "استان تهران، تهران، شهرک غرب" }
  ],
  "specialtiesTitle": "تخصص‌ها",
  "specialties": [
    {
      "title": "متخصص تعمیر هندپیس",
      "desc": "مهارت بالا در تعمیر و نگهداری هندپیس‌های سرعت بالا/پایین و سیستم‌های میکروموتور."
    },
    {
      "title": "تکنسین نگهداری و تعمیرات تجهیزات دندانپزشکی",
      "desc": "متخصص در تعمیر سیستم‌های یونیت، کامپرسور و نگهداری تجهیزات کلینیک‌های دندانپزشکی."
    },
    {
      "title": "تکنسین یونیت و صندلی دندانپزشکی",
      "desc": "تجربه در نصب، تعمیر و سرویس سیستم‌های صندلی و تجهیزات جانبی دندانپزشکی."
    },
    {
      "title": "متخصص استریلیزاسیون و اوتوکلاوها",
      "desc": "تنظیم و نگهداری و تعمیر انواع اتوکلاو استریلیزاسیون تجهیزات دندانپزشکی در کلینیک‌ها."
    },
    {
      "title": "تکنسین تجهیزات تصویربرداری و رادیولوژی دندانپزشکی",
      "desc": "تعمیر و نگهداری و کالیبراسیون دستگاه‌های رادیولوژی دندانپزشکی مانند پانورامیک، CBCT و سنسور."
    }
  ]
}



